hypermapper/__init__.py
hypermapper/_branin_scenario.json
hypermapper/_cli.py
hypermapper/bo.py
hypermapper/cma_es.py
hypermapper/compute_pareto.py
hypermapper/evolution.py
hypermapper/local_search.py
hypermapper/models.py
hypermapper/optimizer.py
hypermapper/pibo.py
hypermapper/plot_hvi.py
hypermapper/plot_model_fit.py
hypermapper/plot_optimization_results.py
hypermapper/plot_pareto.py
hypermapper/prior_optimization.py
hypermapper/profiling.py
hypermapper/random_scalarizations.py
hypermapper/schema.json
hypermapper/space.py
hypermapper/utility_functions.py
hypermapper-2.3.0.dist-info/LICENSE
hypermapper-2.3.0.dist-info/METADATA
hypermapper-2.3.0.dist-info/WHEEL
hypermapper-2.3.0.dist-info/entry_points.txt
hypermapper-2.3.0.dist-info/top_level.txt
hypermapper-2.3.0.dist-info/RECORD
