Metadata-Version: 2.1
Name: hypermapper
Version: 2.3.0
Summary: HyperMapper is a multi-objective black-box optimization tool based on Bayesian Optimization.
Home-page: https://github.com/luinardi/hypermapper
Author: Luigi Nardi
Author-email: luigi.nardi@cs.lth.se
License: UNKNOWN
Platform: UNKNOWN
Classifier: Programming Language :: Python :: 3
Classifier: License :: OSI Approved :: MIT License
Classifier: Operating System :: OS Independent
Requires-Python: >=3.6
License-File: LICENSE
Requires-Dist: cma
Requires-Dist: numpy
Requires-Dist: matplotlib
Requires-Dist: ply
Requires-Dist: jsonschema
Requires-Dist: pandas
Requires-Dist: scikit-learn
Requires-Dist: GPy
Requires-Dist: pyDOE
Requires-Dist: statsmodels
Requires-Dist: ipykernel
Requires-Dist: scipy
Requires-Dist: threadpoolctl
Provides-Extra: plot_hvi
Requires-Dist: pygmo ; extra == 'plot_hvi'
Requires-Dist: statsmodels ; extra == 'plot_hvi'
